image_processing_mr/__init__.py
image_processing_mr/processing/__init__.py
image_processing_mr/processing/combination.py
image_processing_mr/processing/transformation.py
image_processing_mr/utils/__init__.py
image_processing_mr/utils/io.py
image_processing_mr/utils/plot.py
image_processing_mr-0.0.1.dist-info/METADATA
image_processing_mr-0.0.1.dist-info/WHEEL
image_processing_mr-0.0.1.dist-info/top_level.txt
image_processing_mr-0.0.1.dist-info/RECORD
